opencv_jupyter_ui/__init__.py
opencv_jupyter_ui/cv2_imshow.py
opencv_jupyter_ui-1.4.2.dist-info/LICENSE
opencv_jupyter_ui-1.4.2.dist-info/METADATA
opencv_jupyter_ui-1.4.2.dist-info/WHEEL
opencv_jupyter_ui-1.4.2.dist-info/top_level.txt
opencv_jupyter_ui-1.4.2.dist-info/RECORD
