Metadata-Version: 2.1
Name: opencv-jupyter-ui
Version: 1.4.2
Summary: A simple widget to display opencv imshow
Home-page: https://github.com/modaresimr/opencv_jupyter_ui
Author: Seyed Modaresi
Author-email: alim1369@gmail.com
Classifier: Programming Language :: Python :: 3
Classifier: License :: OSI Approved :: Apache Software License
Classifier: Operating System :: OS Independent
License-File: LICENSE
Requires-Dist: ipycanvas
Requires-Dist: jupyter-ui-poll
Requires-Dist: ipywidgets
Requires-Dist: numpy
